{
  "workers": [
    {
      "firstName": "Jennifer",
      "lastName": "Jackson",
      "workplace": "Scrum Master",
      "age": 35,
      "gender": "female",
      "email": "JJ@sohu.com",
      "phone": "+63 732 632 8932",
      "birthDate": "1988-03-13",
      "address": "1845 TS Street",
      "city": "New York",
      "postalCode": "20030",
      "state": "DC",
      "startWork": "2022-04-02",
      "id": 3
    },
    {
      "id": 4,
      "firstName": "Tyler",
      "lastName": "Anderson",
      "age": 33,
      "gender": "male",
      "email": "Tylertoziom@sohu.com",
      "phone": "+63 821 128 2181",
      "birthDate": "1990-12-25",
      "workplace": "Programmer",
      "address": "1245 South Street ",
      "city": "Topeka",
      "postalCode": "20020",
      "state": "KS",
      "startWork": "2023-08-11"
    },
    {
      "id": 5,
      "firstName": "Megan",
      "lastName": "Tylor",
      "age": 28,
      "gender": "female",
      "email": "Tylortoziomalka@sohu.com",
      "phone": "+63 999 655 5514",
      "birthDate": "1995-03-03",
      "workplace": "Manager",
      "address": "0745 Yolo Street",
      "city": "Sacramento",
      "postalCode": "20190",
      "state": "CA",
      "startWork": "2022-05-14"
    },
    {
      "id": 6,
      "firstName": "Kacper",
      "lastName": "Strzelecki",
      "workplace": "Programer",
      "age": "32"
    },
    {
      "id": 7,
      "firstName": "Kacper",
      "lastName": "Strzelecki",
      "workplace": "Chef",
      "age": "32"
    },
    {
      "id": 8,
      "firstName": "Casd",
      "lastName": "asdasd",
      "workplace": "lsflsmdf",
      "age": "23"
    },
    {
      "id": 9,
      "firstName": "rwet",
      "lastName": "wetwe",
      "workplace": "rewtwer",
      "age": "0435"
    },
    {
      "firstName": "asdfasdf",
      "lastName": "asdfasdf",
      "workplace": "asfdf",
      "age": "032",
      "id": 10
    },
    {
      "firstName": "asdfasdf",
      "lastName": "wewafs",
      "workplace": "asdfasdf",
      "age": "0332",
      "id": 12
    },
    {
      "firstName": "sadfasdf",
      "lastName": "sdafas",
      "workplace": "sadfsadf",
      "age": "032",
      "id": 13
    },
    {
      "firstName": "asdfsadf",
      "lastName": "sdfasf",
      "workplace": "sdfasdf",
      "age": "03232",
      "id": 14
    },
    {
      "firstName": "asdfasdf",
      "lastName": "asdfsaf",
      "workplace": "arfsadfsad",
      "age": "03232",
      "id": 15
    },
    {
      "firstName": "Artur",
      "lastName": "Kowalski",
      "workplace": "szef",
      "age": "34",
      "id": 17
    },
    {
      "firstName": "adfsadfs",
      "lastName": "sadfsdfsfd",
      "workplace": "asdfsdf",
      "age": "222",
      "id": 18
    },
    {
      "firstName": "Nicklaus",
      "lastName": "Cruickshank",
      "workplace": "test",
      "age": "1",
      "id": 19
    },
    {
      "firstName": "aaaa",
      "lastName": "aaaa",
      "workplace": "aaa",
      "age": 0,
      "id": 20
    },
    {
      "firstName": "bbbb",
      "lastName": "bbbb",
      "workplace": "bbbb",
      "age": 0,
      "gender": "bbbb",
      "email": "bbbb",
      "phone": "bbbb",
      "birthDate": "bbbb",
      "address": "bbbb",
      "city": "bbbb",
      "postalCode": "bbbb",
      "state": "",
      "startWork": "bbbb",
      "id": 21
    },
    {
      "firstName": "cccc",
      "lastName": "ccccc",
      "workplace": "",
      "age": 0,
      "gender": "",
      "email": "",
      "phone": "",
      "birthDate": "",
      "address": "",
      "city": "",
      "postalCode": "",
      "state": "",
      "startWork": "",
      "id": 22
    },
    {
      "firstName": "zzzz",
      "lastName": "zzzz",
      "workplace": "",
      "age": 0,
      "gender": "",
      "email": "",
      "phone": "",
      "birthDate": "",
      "address": "",
      "city": "",
      "postalCode": "",
      "state": "zzzzz",
      "startWork": "",
      "id": 23
    },
    {
      "firstName": "11111",
      "lastName": "11111",
      "workplace": "11111",
      "age": "5",
      "gender": "11111",
      "email": "11111",
      "phone": "11111",
      "birthDate": "11111",
      "address": "11111",
      "city": "11111",
      "postalCode": "11111",
      "state": "11111",
      "startWork": "11111",
      "id": 24
    },
    {
      "firstName": "",
      "lastName": "",
      "workplace": "",
      "age": 0,
      "gender": "",
      "email": "",
      "phone": "",
      "birthDate": "",
      "address": "",
      "city": "",
      "postalCode": "",
      "state": "",
      "startWork": "",
      "id": 25
    },
    {
      "firstName": "",
      "lastName": "",
      "workplace": "",
      "age": 0,
      "gender": "",
      "email": "",
      "phone": "",
      "birthDate": "",
      "address": "",
      "city": "",
      "postalCode": "",
      "state": "",
      "startWork": "",
      "id": 26
    },
    {
      "firstName": "",
      "lastName": "",
      "workplace": "",
      "age": 0,
      "gender": "",
      "email": "",
      "phone": "",
      "birthDate": "",
      "address": "",
      "city": "",
      "postalCode": "",
      "state": "",
      "startWork": "",
      "id": 27
    },
    {
      "firstName": "",
      "lastName": "",
      "workplace": "",
      "age": 0,
      "gender": "",
      "email": "",
      "phone": "",
      "birthDate": "",
      "address": "",
      "city": "",
      "postalCode": "",
      "state": "",
      "startWork": "",
      "id": 28
    },
    {
      "firstName": "",
      "lastName": "",
      "workplace": "",
      "age": 0,
      "gender": "",
      "email": "",
      "phone": "",
      "birthDate": "",
      "address": "",
      "city": "",
      "postalCode": "",
      "state": "",
      "startWork": "",
      "id": 29
    },
    {
      "firstName": "",
      "lastName": "",
      "workplace": "",
      "age": 0,
      "gender": "",
      "email": "",
      "phone": "",
      "birthDate": "",
      "address": "",
      "city": "",
      "postalCode": "",
      "state": "",
      "startWork": "",
      "id": 30
    }
  ]
}